taug/__init__.py
taug/datasets.py
taug/utils.py
taug/augmenters/__init__.py
taug/augmenters/vae.py
taug-0.1.0.dist-info/LICENSE
taug-0.1.0.dist-info/METADATA
taug-0.1.0.dist-info/WHEEL
taug-0.1.0.dist-info/top_level.txt
taug-0.1.0.dist-info/RECORD
