Metadata-Version: 2.1
Name: taug
Version: 0.1.0
Summary: Time Series Forecasting and Data Augmentation using Deep Generative Models 
Home-page: https://github.com/amirabbasasadi/taug
Author: Amirabbas Asadi
Author-email: amir137825@gmail.com
License: UNKNOWN
Platform: UNKNOWN
Requires-Dist: tensorflow (>=2.0.0)
Requires-Dist: keras
Requires-Dist: tensorflow-addons
Requires-Dist: sktime (>=0.7.0)
